Metadata-Version: 2.1
Name: smartswitchcase
Version: 1.0
Summary: Python libraries of implementation of Switch Case
Home-page: https://github.com/koffiisen/SmartSwitchCase
Author: Joel Koffi ONIPOH
Author-email: koffi_joel.onipoh@isen.yncrea.fr
License: MIT
Download-URL: https://github.com/koffiisen/SmartSwitchCase/blob/main/archive/smartswitchcase-1.0.tar.gz
Keywords: Switch,Case,Switch Case,switch case,switch,case,python switch case,Python switch case,python switch,python library,python libraries,python switch case library,Python Switch Case example
Platform: UNKNOWN
Classifier: Programming Language :: Python
Classifier: Programming Language :: Python :: 2.7
Classifier: Programming Language :: Python :: 3
Classifier: Programming Language :: Python :: 3.1
Classifier: Programming Language :: Python :: 3.2
Classifier: Programming Language :: Python :: 3.3
Classifier: Programming Language :: Python :: 3.4
Classifier: Programming Language :: Python :: 3.5
Classifier: Programming Language :: Python :: 3.6
Classifier: Programming Language :: Python :: 3.7
Classifier: License :: OSI Approved :: MIT License
Classifier: Operating System :: OS Independent
Requires-Python: >=2.7
